axon/__init__.py
axon/client.py
axon/config.ini
axon/config_loader.py
axon/iot_service.py
axon/version.py
axon/certs/bootstrap-certificate.pem.crt
axon/certs/bootstrap-private.pem.key
axon/certs/root.ca.pem
axon_python-1.0.19.dist-info/LICENSE
axon_python-1.0.19.dist-info/METADATA
axon_python-1.0.19.dist-info/WHEEL
axon_python-1.0.19.dist-info/top_level.txt
axon_python-1.0.19.dist-info/RECORD
